django_elasticsearch_dsl_drf_alt/__init__.py
django_elasticsearch_dsl_drf_alt/analyzers.py
django_elasticsearch_dsl_drf_alt/apps.py
django_elasticsearch_dsl_drf_alt/compat.py
django_elasticsearch_dsl_drf_alt/constants.py
django_elasticsearch_dsl_drf_alt/elasticsearch_helpers.py
django_elasticsearch_dsl_drf_alt/helpers.py
django_elasticsearch_dsl_drf_alt/pagination.py
django_elasticsearch_dsl_drf_alt/pip_helpers.py
django_elasticsearch_dsl_drf_alt/serializers.py
django_elasticsearch_dsl_drf_alt/utils.py
django_elasticsearch_dsl_drf_alt/versions.py
django_elasticsearch_dsl_drf_alt/viewsets.py
django_elasticsearch_dsl_drf_alt/wrappers.py
django_elasticsearch_dsl_drf_alt/fields/__init__.py
django_elasticsearch_dsl_drf_alt/fields/common.py
django_elasticsearch_dsl_drf_alt/fields/helpers.py
django_elasticsearch_dsl_drf_alt/fields/nested_fields.py
django_elasticsearch_dsl_drf_alt/filter_backends/__init__.py
django_elasticsearch_dsl_drf_alt/filter_backends/faceted_search.py
django_elasticsearch_dsl_drf_alt/filter_backends/highlight.py
django_elasticsearch_dsl_drf_alt/filter_backends/mixins.py
django_elasticsearch_dsl_drf_alt/filter_backends/source.py
django_elasticsearch_dsl_drf_alt/filter_backends/aggregations/__init__.py
django_elasticsearch_dsl_drf_alt/filter_backends/aggregations/bucket_aggregations.py
django_elasticsearch_dsl_drf_alt/filter_backends/aggregations/metrics_aggregations.py
django_elasticsearch_dsl_drf_alt/filter_backends/aggregations/pipeline_aggregations.py
django_elasticsearch_dsl_drf_alt/filter_backends/filtering/__init__.py
django_elasticsearch_dsl_drf_alt/filter_backends/filtering/common.py
django_elasticsearch_dsl_drf_alt/filter_backends/filtering/geo_spatial.py
django_elasticsearch_dsl_drf_alt/filter_backends/filtering/ids.py
django_elasticsearch_dsl_drf_alt/filter_backends/filtering/nested.py
django_elasticsearch_dsl_drf_alt/filter_backends/filtering/post_filter.py
django_elasticsearch_dsl_drf_alt/filter_backends/ordering/__init__.py
django_elasticsearch_dsl_drf_alt-0.22.9.dist-info/LICENSE_GPL2.0.txt
django_elasticsearch_dsl_drf_alt-0.22.9.dist-info/LICENSE_LGPL_2.1.txt
django_elasticsearch_dsl_drf_alt-0.22.9.dist-info/METADATA
django_elasticsearch_dsl_drf_alt-0.22.9.dist-info/WHEEL
django_elasticsearch_dsl_drf_alt-0.22.9.dist-info/top_level.txt
django_elasticsearch_dsl_drf_alt-0.22.9.dist-info/RECORD
