Metadata-Version: 2.1
Name: django-elasticsearch-dsl-drf-alt
Version: 0.22.9
Summary: Custom version of django-elasticsearch-dsl-drf.
Home-page: https://github.com/anjalikdas/django-elasticsearch-dsl-drf
Author: Anjali
Author-email: anjallikdas@gmail.com
License: GPL-2.0-only OR LGPL-2.1-or-later
Project-URL: Bug Tracker, https://github.com/barseghyanartur/django-elasticsearch-dsl-drf/issues
Project-URL: Documentation, https://django-elasticsearch-dsl-drf.readthedocs.io/
Project-URL: Source Code, https://github.com/barseghyanartur/django-elasticsearch-dsl-drf
Project-URL: Changelog, https://django-elasticsearch-dsl-drf.readthedocs.io/en/latest/changelog.html
Keywords: django,elasticsearch,elasticsearch-dsl,django rest framework
Platform: UNKNOWN
Classifier: Programming Language :: Python :: 3.6
Classifier: Programming Language :: Python :: 3.7
Classifier: Programming Language :: Python :: 3.8
Classifier: Programming Language :: Python :: 3.9
Classifier: Environment :: Web Environment
Classifier: License :: OSI Approved :: GNU General Public License v2 (GPLv2)
Classifier: License :: OSI Approved :: GNU Lesser General Public License v2 or later (LGPLv2+)
Classifier: Framework :: Django
Classifier: Intended Audience :: Developers
Classifier: Operating System :: OS Independent
Classifier: Development Status :: 4 - Beta
Requires-Python: >=2.7
License-File: LICENSE_GPL2.0.txt
License-File: LICENSE_LGPL_2.1.txt
Requires-Dist: six>=1.9
Requires-Dist: django-nine>=0.2
Requires-Dist: django-elasticsearch-dsl>=6.4.1
Requires-Dist: elasticsearch-dsl
Requires-Dist: elasticsearch
Requires-Dist: djangorestframework
